Readme.txt
setup.cfg
setup.py
emaildata/__init__.py
emaildata/attachment.py
emaildata/metadata.py
emaildata/text.py
emaildata.egg-info/PKG-INFO
emaildata.egg-info/SOURCES.txt
emaildata.egg-info/dependency_links.txt
emaildata.egg-info/entry_points.txt
emaildata.egg-info/requires.txt
emaildata.egg-info/top_level.txt
emaildata.egg-info/zip-safe