Metadata-Version: 1.1
Name: emaildata
Version: 0.3.4
Summary: Python package for extracting metadata, text, html and attachements from email messages.
Home-page: https://bitbucket.org/karelverdecia/emaildata/wiki/Home
Author: Karel Antonio Verdecia Ortiz
Author-email: kverdecia@gmail.com
License: LGPL3
Download-URL: https://bitbucket.org/karelverdecia/emaildata/
Keywords: email,rfc822
Platform: UNKNOWN
Classifier: Topic :: Communications :: Email
Classifier: License :: OSI Approved :: GNU Lesser General Public License v3 (LGPLv3)
Classifier: Operating System :: OS Independent
Classifier: Topic :: Text Processing
